odoo/addons/beesdoo_purchase/README.rst
odoo/addons/beesdoo_purchase/__init__.py
odoo/addons/beesdoo_purchase/__manifest__.py
odoo/addons/beesdoo_purchase/i18n/fr_BE.po
odoo/addons/beesdoo_purchase/models/__init__.py
odoo/addons/beesdoo_purchase/models/purchase.py
odoo/addons/beesdoo_purchase/readme/CONTRIBUTORS.rst
odoo/addons/beesdoo_purchase/readme/DESCRIPTION.rst
odoo/addons/beesdoo_purchase/report/report_purchaseorder.xml
odoo/addons/beesdoo_purchase/static/description/index.html
odoo/addons/beesdoo_purchase/views/purchase_order.xml
odoo12_addon_beesdoo_purchase-12.0.1.1.0.99.dev4.dist-info/METADATA
odoo12_addon_beesdoo_purchase-12.0.1.1.0.99.dev4.dist-info/WHEEL
odoo12_addon_beesdoo_purchase-12.0.1.1.0.99.dev4.dist-info/top_level.txt
odoo12_addon_beesdoo_purchase-12.0.1.1.0.99.dev4.dist-info/RECORD
