Metadata-Version: 2.1
Name: odoo12-addon-beesdoo-purchase
Version: 12.0.1.1.0.99.dev4
Summary: - Adds a 'Responsible' field to purchase orders, - A filter w.r.t. the mail sellers is placed on the products field of a purchase order.
Home-page: https://github.com/beescoop/Obeesdoo
Author: Beescoop - Cellule IT, Coop IT Easy SCRLfs
License: AGPL-3
Platform: UNKNOWN
Classifier: Programming Language :: Python
Classifier: Framework :: Odoo
Classifier: License :: OSI Approved :: GNU Affero General Public License v3
Requires-Python: >=3.5
Requires-Dist: odoo12-addon-beesdoo-product
Requires-Dist: odoo (<12.1dev,>=12.0a)
